[{"__type__":"cc.SpriteFrame","content":{"name":"9004","texture":"1e7ea5b79","rect":[434,415,19,50],"offset":[0,0],"originalSize":[19,50],"capInsets":[0,0,0,0]}},[{"__type__":"cc.Prefab","_name":"9004","data":{"__id__":1}},{"__type__":"cc.Node","_name":"9004","_children":[{"__id__":2},{"__id__":3},{"__id__":5}],"_level":1,"_components":[{"__type__":"cc.Sprite","node":{"__id__":1},"_spriteFrame":{"__uuid__":"9atYkO7WlIDZgRw8Oyst4L"}},{"__type__":"cc.RigidBody","node":{"__id__":1},"_gravityScale":0,"enabledContactListener":true},{"__type__":"cc.PhysicsBoxCollider","node":{"__id__":1},"tag":9000,"_restitution":0.2,"_size":{"__type__":"cc.Size","width":19,"height":50}},{"__type__":"4c1c428v7JNRIHTHcZWBN/4","node":{"__id__":1}}],"_prefab":{"__type__":"cc.PrefabInfo","root":{"__id__":1},"asset":{"__uuid__":"dbbrVTjyNGGIer9aI1N5bS"},"fileId":"55zkh5355Dorw9F/0L/3Tt"},"_contentSize":{"__type__":"cc.Size","width":19,"height":50},"_position":{"__type__":"cc.Vec3","x":6.7,"y":45.4},"_scale":{"__type__":"cc.Vec3","x":1,"y":1,"z":1},"groupIndex":1},{"__type__":"cc.Node","_name":"shadow","_parent":{"__id__":1},"_level":2,"_components":[{"__type__":"cc.MotionStreak","node":{"__id__":2},"_fadeTime":0.1,"_stroke":30,"_texture":{"__uuid__":"53oMqOeMhJS6F+ytmohDKN"},"_color":{"__type__":"cc.Color","r":244,"g":231,"b":126,"a":138},"_fastMode":true}],"_prefab":{"__type__":"cc.PrefabInfo","root":{"__id__":1},"asset":{"__uuid__":"dbbrVTjyNGGIer9aI1N5bS"},"fileId":"4bWi6F77RBd7Am0t9EDt6G"},"_opacity":113,"_contentSize":{"__type__":"cc.Size","width":20,"height":40},"_scale":{"__type__":"cc.Vec3","x":1,"y":1,"z":1},"_quat":{"__type__":"cc.Quat","z":-0.9238795325112867,"w":0.38268343236508984}},{"__type__":"cc.Node","_name":"9004","_parent":{"__id__":1},"_children":[{"__id__":4}],"_level":2,"_components":[{"__type__":"cc.Sprite","node":{"__id__":3},"_spriteFrame":{"__uuid__":"9atYkO7WlIDZgRw8Oyst4L"}}],"_prefab":{"__type__":"cc.PrefabInfo","root":{"__id__":1},"asset":{"__uuid__":"dbbrVTjyNGGIer9aI1N5bS"},"fileId":"9bGRAGYH5FVo/tztVYccri"},"_contentSize":{"__type__":"cc.Size","width":19,"height":50},"_position":{"__type__":"cc.Vec3","x":-16.7,"y":-88.3},"_scale":{"__type__":"cc.Vec3","x":1,"y":1,"z":1},"groupIndex":1},{"__type__":"cc.Node","_name":"shadow","_parent":{"__id__":3},"_level":2,"_components":[{"__type__":"cc.MotionStreak","node":{"__id__":4},"_fadeTime":0.1,"_stroke":30,"_texture":{"__uuid__":"53oMqOeMhJS6F+ytmohDKN"},"_color":{"__type__":"cc.Color","r":244,"g":231,"b":126,"a":138},"_fastMode":true}],"_prefab":{"__type__":"cc.PrefabInfo","root":{"__id__":1},"asset":{"__uuid__":"dbbrVTjyNGGIer9aI1N5bS"},"fileId":"3fh7xz6mxN1pKWfs2imcN9"},"_opacity":113,"_contentSize":{"__type__":"cc.Size","width":20,"height":40},"_scale":{"__type__":"cc.Vec3","x":1,"y":1,"z":1},"_quat":{"__type__":"cc.Quat","z":-0.9238795325112867,"w":0.38268343236508984}},{"__type__":"cc.Node","_name":"9004","_parent":{"__id__":1},"_children":[{"__id__":6}],"_level":2,"_components":[{"__type__":"cc.Sprite","node":{"__id__":5},"_spriteFrame":{"__uuid__":"9atYkO7WlIDZgRw8Oyst4L"}}],"_prefab":{"__type__":"cc.PrefabInfo","root":{"__id__":1},"asset":{"__uuid__":"dbbrVTjyNGGIer9aI1N5bS"},"fileId":"736W904eVGW6tiC6kinu6B"},"_contentSize":{"__type__":"cc.Size","width":19,"height":50},"_position":{"__type__":"cc.Vec3","x":24.8,"y":-135.2},"_scale":{"__type__":"cc.Vec3","x":1,"y":1,"z":1},"groupIndex":1},{"__type__":"cc.Node","_name":"shadow","_parent":{"__id__":5},"_level":2,"_components":[{"__type__":"cc.MotionStreak","node":{"__id__":6},"_fadeTime":0.1,"_stroke":30,"_texture":{"__uuid__":"53oMqOeMhJS6F+ytmohDKN"},"_color":{"__type__":"cc.Color","r":244,"g":231,"b":126,"a":138},"_fastMode":true}],"_prefab":{"__type__":"cc.PrefabInfo","root":{"__id__":1},"asset":{"__uuid__":"dbbrVTjyNGGIer9aI1N5bS"},"fileId":"40uG4UvLxFPp1vFIy7KfLo"},"_opacity":113,"_contentSize":{"__type__":"cc.Size","width":20,"height":40},"_scale":{"__type__":"cc.Vec3","x":1,"y":1,"z":1},"_quat":{"__type__":"cc.Quat","z":-0.9238795325112867,"w":0.38268343236508984}}]]