[{"__type__":"cc.SpriteFrame","content":{"name":"coinsLight","texture":"1dc9527fe","rect":[3,3,462,470],"offset":[0,0],"originalSize":[472,472],"capInsets":[0,0,0,0]}},{"__type__":"cc.SpriteFrame","content":{"name":"img","texture":"1dc9527fe","rect":[858,3,78,87],"offset":[0,0],"originalSize":[78,87],"rotated":1,"capInsets":[0,0,0,0]}},{"__type__":"cc.SpriteFrame","content":{"name":"coins","texture":"1dc9527fe","rect":[471,3,270,154],"offset":[-14,-6],"originalSize":[300,200],"rotated":1,"capInsets":[0,0,0,0]}},{"__type__":"cc.SpriteFrame","content":{"name":"bt1","texture":"18d113db8","rect":[584,855,269,100],"offset":[0,0],"originalSize":[269,100],"capInsets":[0,0,0,0]}},{"__type__":"cc.SpriteFrame","content":{"name":"bg3","texture":"1682258cb","rect":[3,3,658,670],"offset":[0,-1],"originalSize":[660,672],"capInsets":[187,180,212,187]}},{"__type__":"cc.SpriteFrame","content":{"name":"default_sprite_splash","texture":"02delMVqdBD70a/HSD99FK","rect":[0,0,2,2],"offset":[0,0],"originalSize":[2,2],"capInsets":[0,0,0,0]}},{"__type__":"cc.SpriteFrame","content":{"name":"txt","texture":"1dc9527fe","rect":[471,279,381,49],"offset":[0,0],"originalSize":[381,49],"capInsets":[0,0,0,0]}},{"__type__":"cc.SpriteFrame","content":{"name":"receive","texture":"1dc9527fe","rect":[3,479,112,29],"offset":[0,0],"originalSize":[112,29],"capInsets":[0,0,0,0]}},{"__type__":"cc.SpriteFrame","content":{"name":"videoTag","texture":"18d113db8","rect":[645,961,49,38],"offset":[0,0],"originalSize":[49,38],"rotated":1,"capInsets":[0,0,0,0]}},[{"__type__":"cc.Prefab","_name":"offlineRewardPanel","data":{"__id__":1}},{"__type__":"cc.Node","_name":"offlineRewardPanel","_children":[{"__id__":2},{"__id__":3}],"_level":1,"_components":[{"__type__":"cc.Widget","node":{"__id__":1},"_alignFlags":45},{"__type__":"b80f0WwwP9NIo9tdlZnY3sH","node":{"__id__":1},"coinsLight":{"__id__":5},"title":{"__id__":10},"coins":{"__id__":6}}],"_prefab":{"__type__":"cc.PrefabInfo","root":{"__id__":1},"asset":{"__uuid__":"f9oQhTkvFLj6DN6qgUuGCy"},"fileId":"aerQvx8qBHWq45Ccp38r6T"},"_contentSize":{"__type__":"cc.Size","width":750,"height":1334},"_position":{"__type__":"cc.Vec3","x":375,"y":667},"_scale":{"__type__":"cc.Vec3","x":1,"y":1,"z":1}},{"__type__":"cc.Node","_name":"background","_parent":{"__id__":1},"_level":2,"_components":[{"__type__":"cc.Sprite","node":{"__id__":2},"_spriteFrame":{"__uuid__":"a2MjXRFdtLlYQ5ouAFv/+R"},"_sizeMode":0},{"__type__":"cc.Widget","node":{"__id__":2},"_alignFlags":45,"_originalWidth":100,"_originalHeight":100},{"__type__":"cc.BlockInputEvents","node":{"__id__":2}}],"_prefab":{"__type__":"cc.PrefabInfo","root":{"__id__":1},"asset":{"__uuid__":"f9oQhTkvFLj6DN6qgUuGCy"},"fileId":"fb5ZHSg6NGa7U5VC2KY1kF"},"_opacity":180,"_color":{"__type__":"cc.Color"},"_contentSize":{"__type__":"cc.Size","width":750,"height":1334},"_scale":{"__type__":"cc.Vec3","x":1,"y":1,"z":1}},{"__type__":"cc.Node","_name":"content","_parent":{"__id__":1},"_children":[{"__id__":4}],"_level":3,"_components":[{"__type__":"cc.Widget","node":{"__id__":3},"_alignFlags":45}],"_prefab":{"__type__":"cc.PrefabInfo","root":{"__id__":1},"asset":{"__uuid__":"f9oQhTkvFLj6DN6qgUuGCy"},"fileId":"43/4/6X25HXqbyE4nb+uDR"},"_contentSize":{"__type__":"cc.Size","width":750,"height":1334},"_scale":{"__type__":"cc.Vec3","x":1,"y":1,"z":1}},{"__type__":"cc.Node","_name":"bg","_parent":{"__id__":3},"_children":[{"__id__":5},{"__id__":6},{"__id__":7},{"__id__":8},{"__id__":9},{"__id__":11},{"__id__":17}],"_level":4,"_components":[{"__type__":"cc.Sprite","node":{"__id__":4},"_spriteFrame":{"__uuid__":"76g1S8jgpCOauH8xwn6K4p"},"_type":1,"_sizeMode":0},{"__type__":"cc.Widget","node":{"__id__":4},"_alignFlags":20,"_bottom":657}],"_prefab":{"__type__":"cc.PrefabInfo","root":{"__id__":1},"asset":{"__uuid__":"f9oQhTkvFLj6DN6qgUuGCy"},"fileId":"162J3oJCJIJakPwhTob+iG"},"_contentSize":{"__type__":"cc.Size","width":660,"height":626},"_position":{"__type__":"cc.Vec3","y":303},"_scale":{"__type__":"cc.Vec3","x":1,"y":1,"z":1}},{"__type__":"cc.Node","_name":"coinsLight","_parent":{"__id__":4},"_level":5,"_components":[{"__type__":"cc.Sprite","node":{"__id__":5},"_spriteFrame":{"__uuid__":"16XHrQAoRPJYciNeTTnOZb"}}],"_prefab":{"__type__":"cc.PrefabInfo","root":{"__id__":1},"asset":{"__uuid__":"f9oQhTkvFLj6DN6qgUuGCy"},"fileId":"96GkJRBw9ERbDEnjAyhZLi"},"_contentSize":{"__type__":"cc.Size","width":464,"height":470},"_position":{"__type__":"cc.Vec3","y":-31},"_scale":{"__type__":"cc.Vec3","x":1,"y":1,"z":1}},{"__type__":"cc.Node","_name":"coins","_parent":{"__id__":4},"_level":5,"_components":[{"__type__":"cc.Sprite","node":{"__id__":6},"_spriteFrame":{"__uuid__":"4fIJTUqtFOW4YWBSzlUiQ9"}}],"_prefab":{"__type__":"cc.PrefabInfo","root":{"__id__":1},"asset":{"__uuid__":"f9oQhTkvFLj6DN6qgUuGCy"},"fileId":"d7LMEpqbdMjIpu2znUX8r5"},"_contentSize":{"__type__":"cc.Size","width":270,"height":154},"_position":{"__type__":"cc.Vec3","x":-20,"y":-3},"_scale":{"__type__":"cc.Vec3","x":1,"y":1,"z":1}},{"__type__":"cc.Node","_name":"txtTitle","_parent":{"__id__":4},"_level":5,"_components":[{"__type__":"cc.Sprite","node":{"__id__":7},"_spriteFrame":{"__uuid__":"c9VY2qQK9B0r4dYkdkHwg4"},"_sizeMode":0}],"_prefab":{"__type__":"cc.PrefabInfo","root":{"__id__":1},"asset":{"__uuid__":"f9oQhTkvFLj6DN6qgUuGCy"},"fileId":"f2cuvTKwZOCKC3moDDz51p"},"_contentSize":{"__type__":"cc.Size","width":381,"height":49},"_position":{"__type__":"cc.Vec3","x":-1,"y":258},"_scale":{"__type__":"cc.Vec3","x":1,"y":1,"z":1}},{"__type__":"cc.Node","_name":"text","_parent":{"__id__":4},"_level":5,"_components":[{"__type__":"cc.Label","node":{"__id__":8},"_useOriginalSize":false,"_string":"While you were offline, we collected","_N$string":"While you were offline, we collected","_fontSize":35,"_lineHeight":34,"_N$horizontalAlign":1,"_N$verticalAlign":1,"_N$overflow":2}],"_prefab":{"__type__":"cc.PrefabInfo","root":{"__id__":1},"asset":{"__uuid__":"f9oQhTkvFLj6DN6qgUuGCy"},"fileId":"761YnELMVEaYCnAnYSHW9y"},"_contentSize":{"__type__":"cc.Size","width":553.8,"height":34},"_position":{"__type__":"cc.Vec3","y":163},"_scale":{"__type__":"cc.Vec3","x":1,"y":1,"z":1}},{"__type__":"cc.Node","_name":"count","_parent":{"__id__":4},"_level":5,"_components":[{"__id__":10}],"_prefab":{"__type__":"cc.PrefabInfo","root":{"__id__":1},"asset":{"__uuid__":"f9oQhTkvFLj6DN6qgUuGCy"},"fileId":"1bA2V50F1DYJXSMdf9yqVN"},"_contentSize":{"__type__":"cc.Size","height":50},"_position":{"__type__":"cc.Vec3","y":-107},"_scale":{"__type__":"cc.Vec3","x":1,"y":1,"z":1}},{"__type__":"cc.Label","node":{"__id__":9},"_useOriginalSize":false,"_N$file":{"__uuid__":"11ZueCKC5DOKYzuc/wMWtg"},"_isSystemFontUsed":false,"_N$horizontalAlign":1,"_N$verticalAlign":1},{"__type__":"cc.Node","_name":"doubleReceiveBtn","_parent":{"__id__":4},"_children":[{"__id__":12},{"__id__":14}],"_level":5,"_components":[{"__type__":"cc.Sprite","node":{"__id__":11},"_spriteFrame":{"__uuid__":"690FD6U8dC9L1ZTAtVujVY"}},{"__type__":"cc.Button","node":{"__id__":11},"zoomScale":0.9,"clickEvents":[{"__type__":"cc.ClickEvent","target":{"__id__":1},"_componentId":"b80f0WwwP9NIo9tdlZnY3sH","handler":"onDoubleReceiveDiamondBtn"}],"_N$transition":3,"transition":3}],"_prefab":{"__type__":"cc.PrefabInfo","root":{"__id__":1},"asset":{"__uuid__":"f9oQhTkvFLj6DN6qgUuGCy"},"fileId":"02xHURHDlNjJHiwtkWNC98"},"_contentSize":{"__type__":"cc.Size","width":269,"height":100},"_position":{"__type__":"cc.Vec3","y":-243},"_scale":{"__type__":"cc.Vec3","x":1,"y":1,"z":1}},{"__type__":"cc.Node","_name":"img","_parent":{"__id__":11},"_children":[{"__id__":13}],"_level":5,"_components":[{"__type__":"cc.Sprite","node":{"__id__":12},"_spriteFrame":{"__uuid__":"2a2e60nMtOc4si5QaOzIbz"}}],"_prefab":{"__type__":"cc.PrefabInfo","root":{"__id__":1},"asset":{"__uuid__":"f9oQhTkvFLj6DN6qgUuGCy"},"fileId":"28Xq4ZV9xKf4SwwyNV9GRk"},"_contentSize":{"__type__":"cc.Size","width":78,"height":87},"_position":{"__type__":"cc.Vec3","x":115,"y":33},"_scale":{"__type__":"cc.Vec3","x":1,"y":1,"z":1}},{"__type__":"cc.Node","_name":"New Label","_parent":{"__id__":12},"_level":6,"_components":[{"__type__":"cc.Label","node":{"__id__":13},"_useOriginalSize":false,"_string":"X2","_N$string":"X2","_lineHeight":30,"_N$file":{"__uuid__":"79g16BLSpKP4/udaNIED8l"},"_isSystemFontUsed":false,"_N$horizontalAlign":1,"_N$verticalAlign":1}],"_prefab":{"__type__":"cc.PrefabInfo","root":{"__id__":1},"asset":{"__uuid__":"f9oQhTkvFLj6DN6qgUuGCy"},"fileId":"a10YlfZodAKovQytd75zWh"},"_contentSize":{"__type__":"cc.Size","width":58.75,"height":37.5},"_position":{"__type__":"cc.Vec3","x":0.8,"y":2.5},"_scale":{"__type__":"cc.Vec3","x":1,"y":1,"z":1}},{"__type__":"cc.Node","_name":"New Node","_parent":{"__id__":11},"_children":[{"__id__":15},{"__id__":16}],"_level":6,"_prefab":{"__type__":"cc.PrefabInfo","root":{"__id__":1},"asset":{"__uuid__":"f9oQhTkvFLj6DN6qgUuGCy"},"fileId":"88e0zipaBDaYmVzewQ5gHQ"},"_contentSize":{"__type__":"cc.Size","width":180,"height":100},"_scale":{"__type__":"cc.Vec3","x":1,"y":1,"z":1}},{"__type__":"cc.Node","_name":"videoTag","_parent":{"__id__":14},"_level":7,"_components":[{"__type__":"cc.Sprite","node":{"__id__":15},"_spriteFrame":{"__uuid__":"f6P5fnMm9OyIqPD3s0utOt"}}],"_prefab":{"__type__":"cc.PrefabInfo","root":{"__id__":1},"asset":{"__uuid__":"f9oQhTkvFLj6DN6qgUuGCy"},"fileId":"74RAfLwSBD+55cIkwgtC+j"},"_contentSize":{"__type__":"cc.Size","width":49,"height":38},"_position":{"__type__":"cc.Vec3","x":-74.5,"y":-0.3},"_scale":{"__type__":"cc.Vec3","x":1,"y":1,"z":1}},{"__type__":"cc.Node","_name":"receive","_parent":{"__id__":14},"_level":7,"_components":[{"__type__":"cc.Sprite","node":{"__id__":16},"_spriteFrame":{"__uuid__":"d0lqwlDsZCWboL2Iu5zu69"},"_sizeMode":0}],"_prefab":{"__type__":"cc.PrefabInfo","root":{"__id__":1},"asset":{"__uuid__":"f9oQhTkvFLj6DN6qgUuGCy"},"fileId":"60DiywYslCtYeQzMkzsQpT"},"_contentSize":{"__type__":"cc.Size","width":112,"height":29},"_position":{"__type__":"cc.Vec3","x":15},"_scale":{"__type__":"cc.Vec3","x":1,"y":1,"z":1}},{"__type__":"cc.Node","_name":"ReceiveBtn","_parent":{"__id__":4},"_children":[{"__id__":18}],"_level":5,"_components":[{"__type__":"cc.RichText","node":{"__id__":17},"_N$string":"Claim","_N$horizontalAlign":1,"_N$lineHeight":50},{"__type__":"cc.Button","node":{"__id__":17},"zoomScale":0.9,"clickEvents":[{"__type__":"cc.ClickEvent","target":{"__id__":1},"_componentId":"b80f0WwwP9NIo9tdlZnY3sH","handler":"onReceiveDiamondBtn"}],"_N$transition":3,"transition":3},{"__type__":"d574alL7/pK0ocjB87+fwTI","node":{"__id__":17}}],"_prefab":{"__type__":"cc.PrefabInfo","root":{"__id__":1},"asset":{"__uuid__":"f9oQhTkvFLj6DN6qgUuGCy"},"fileId":"d8u37OYfJEl6DBs41zh+cu"},"_contentSize":{"__type__":"cc.Size","width":102.23,"height":50},"_position":{"__type__":"cc.Vec3","y":-341},"_scale":{"__type__":"cc.Vec3","x":1,"y":1,"z":1}},{"__type__":"cc.PrivateNode","_name":"RICHTEXT_CHILD","_parent":{"__id__":17},"_level":6,"_components":[{"__type__":"cc.Label","node":{"__id__":18},"_string":"Claim","_N$string":"Claim","_lineHeight":50,"_N$verticalAlign":1}],"_prefab":{"__type__":"cc.PrefabInfo","root":{"__id__":1},"asset":{"__uuid__":"f9oQhTkvFLj6DN6qgUuGCy"},"fileId":"29Ri+39k9GP7oykU2eYxJx"},"_contentSize":{"__type__":"cc.Size","width":102.23,"height":50},"_anchorPoint":{"__type__":"cc.Vec2"},"_position":{"__type__":"cc.Vec3","x":-51.115,"y":-25},"_scale":{"__type__":"cc.Vec3","x":1,"y":1,"z":1}}]]