{"__type__":"cc.SpriteAtlas","_spriteFrames":{"top":{"__uuid__":"bcAYcJMxRPr69i0duL5RXd"},"caibg":{"__uuid__":"807r3f0KBCPaLdVDrM2Tta"},"start":{"__uuid__":"53tHtLkddMmLXGKuRbrWdU"},"trialTitle":{"__uuid__":"c6O3Lf/gBArYwqQTLgPA/y"},"addxiaochengxu":{"__uuid__":"dblDdz+L5MrqyCtnvtLc5U"},"caitext":{"__uuid__":"8e1gMMysFH+qpRE0wn63+N"},"role_1008":{"__uuid__":"1b4xZQvFVGLrNtkY3EurOn"},"xiaochengxubg":{"__uuid__":"ae/InPavhGo74ZnarHhheY"},"lixiantext":{"__uuid__":"d3StHuVpdOA6FfS1HsYaBi"},"wenzikuang":{"__uuid__":"b3BkkkYMFCAYhNVe8tdDA2"},"trial":{"__uuid__":"f7nFsU6y9PTaxtvTsfHkPX"},"bg":{"__uuid__":"63pWeTKq1AsoHPloCLdOBU"},"jinbijiangliwenzi":{"__uuid__":"31JYaZ9gxLlIhMYPLSbtke"},"yidongtext":{"__uuid__":"79TOXsd0lDSYzuKsIkgyUL"},"role_1014":{"__uuid__":"c1hGLCL8pEw72y6ddUcYtI"},"role_1015":{"__uuid__":"cc4RakrkRKdZBFp/rf5wqY"},"role_1007":{"__uuid__":"ffR4f08ctBEYzZh2QA7ECN"},"tuijian":{"__uuid__":"1aBGOVBc1Ig5+Fb5RAUD1c"},"jinbizhuanshibg":{"__uuid__":"99A2rZhL1OzralvZo45/nH"},"role_1009":{"__uuid__":"6bPexKmu9IA6DjjRYYRThd"},"role_1006":{"__uuid__":"12P/Nom7JHxIqUIdDFZP9x"},"xiaoxinxin":{"__uuid__":"dfxrrxwyhNEJx0pdHJlUku"},"role_1012":{"__uuid__":"73+CIrZhNFHr0vCzAtzORz"},"role_1002":{"__uuid__":"bfpRrBTw5NyL2/56hTmKLY"},"jingbijia":{"__uuid__":"1ehpKBmClGW5Y6jHb9OATe"},"role_1001":{"__uuid__":"fas32IuC9HfaEL5AzvnMpc"},"tubiaodi":{"__uuid__":"97NOz0jgRMzaXL8xYRYXRG"},"addxiaochengxubox":{"__uuid__":"5aFsyR+NlE5oUiX7ihZ/nQ"},"role_1004":{"__uuid__":"a6eDXtRBxJCqDzu8F6jvtk"},"role_1003":{"__uuid__":"11A/yFixNHzJEeULNuXCub"},"role_1013":{"__uuid__":"192viE8yNN3YWBnqUDMwlc"},"role_1011":{"__uuid__":"1c3Ok1zwZFo4NVaLEy259e"},"role_1010":{"__uuid__":"8bDqz9fJJFH5EwDUYerA6z"},"role_1005":{"__uuid__":"f70PKn62RL8YgOFc1OFSPX"},"lihe":{"__uuid__":"efCmpi60VH9IUUZt9ug8tt"},"qinadao":{"__uuid__":"28uHVgf2REFIvs88PaThpx"},"paihang":{"__uuid__":"00XlOGZ5RHbrSkoKrjkwNN"},"shezhi":{"__uuid__":"d7oZi+DxZIl7O0pEo/gtWK"},"gold":{"__uuid__":"6eWnmoSbpF1o1keCpQUHQD"},"logo":{"__uuid__":"a0XWklW81HEJksOzTB0QMG"},"jinbijinagli":{"__uuid__":"29dA9PIg5LSruHWhkU3AXF"},"lixianshouyi":{"__uuid__":"085azxdfxBka++q6cMAiJV"},"xuanding":{"__uuid__":"c6MbMip6ZIFLwepfiILkrY"},"qianghua":{"__uuid__":"cdHIl33+lNr6s9KSqKzkmr"},"weixuanzhong":{"__uuid__":"47mOFC7utEu6s5vyYPK3ZT"},"shou":{"__uuid__":"cbzONPaadPTa8JI6cPZEGq"},"xuanzhong":{"__uuid__":"cfq8zsP2pH3bjR7QJPdZQQ"},"addxiaochengxilight":{"__uuid__":"701Iu1o2JGl6dPD9kQUeCH"},"caibiankuang":{"__uuid__":"fczzRF6dZAcpz+qPZkPhtD"},"caiicon":{"__uuid__":"99PJeneHZMs7qp4i/HHkMv"},"yidongspeed":{"__uuid__":"59Og5Ndg5Jg6MQ9ppCuwSk"}}}